ipxactschema/__init__.py
ipxactschema/py.typed
ipxactschema-1.0.0a0.dist-info/LICENSE
ipxactschema-1.0.0a0.dist-info/METADATA
ipxactschema-1.0.0a0.dist-info/WHEEL
ipxactschema-1.0.0a0.dist-info/top_level.txt
ipxactschema-1.0.0a0.dist-info/RECORD
